demo_pack1/__init__.py
demo_pack1/example.py
demo_pack1-0.0.2.dist-info/METADATA
demo_pack1-0.0.2.dist-info/WHEEL
demo_pack1-0.0.2.dist-info/entry_points.txt
demo_pack1-0.0.2.dist-info/top_level.txt
demo_pack1-0.0.2.dist-info/RECORD
