Metadata-Version: 2.4
Name: demo-pack1
Version: 0.0.2
Summary: A demo Python package
Author-email: User <user@example.com>
License: MIT
Requires-Python: >=3.8
